cmssign/__init__.py
cmssign/cmssign-1.0-SNAPSHOT.jar
cmssign/cmssign.py
cmssign/ui.py
cmssign-0.0.5.dist-info/METADATA
cmssign-0.0.5.dist-info/WHEEL
cmssign-0.0.5.dist-info/entry_points.txt
cmssign-0.0.5.dist-info/top_level.txt
cmssign-0.0.5.dist-info/RECORD
