Metadata-Version: 2.1
Name: cmssign
Version: 0.0.5
Summary: Tool for cms signature
Home-page: UNKNOWN
License: Apache
Platform: UNKNOWN
Classifier: Programming Language :: Python :: 3
Classifier: License :: OSI Approved :: Apache Software License
Classifier: Operating System :: OS Independent
Requires-Python: >= 3.6
Requires-Dist: pip (>=21.0)
Requires-Dist: cryptography (>=36.0.0)
Requires-Dist: asn1crypto (>=1.3.0)
